Signature_pywrapper/__init__.py
Signature_pywrapper/commons-cli-1.5.0.jar
Signature_pywrapper/eSignature.jar
Signature_pywrapper/signature_wrapper.py
Signature_pywrapper/signatures-1.2-SNAPSHOT.jar
Signature_pywrapper/utils.py
Signature_pywrapper-0.0.2.post1.dist-info/LICENSE
Signature_pywrapper-0.0.2.post1.dist-info/METADATA
Signature_pywrapper-0.0.2.post1.dist-info/WHEEL
Signature_pywrapper-0.0.2.post1.dist-info/top_level.txt
Signature_pywrapper-0.0.2.post1.dist-info/RECORD
